[
  {
    "nomor": "6285890809066"
  },
  {
    "nomor": "6285169655568"
  },
  {
    "nomor": "6285704572935"
  },
  {
    "nomor": "6281373129138"
  },
  {
    "nomor": "6285251507293"
  },
  {
    "nomor": "6281226215775"
  },
  {
    "nomor": "6282178203525"
  },
  {
    "nomor": "6285141000337"
  },
  {
    "nomor": "628126215775"
  },
  {
    "nomor": "62895707382000"
  },
  {
    "nomor": "62882008540926"
  },
  {
    "nomor": "628817456634"
  },
  {
    "nomor": "6283141072141"
  },
  {
    "nomor": "6289675934560"
  },
  {
    "nomor": "6288980726375"
  }
]